.gitignore
MANIFEST.in
Makefile
README.md
requirements.txt
setup.py
.github/workflows/pythonpackage.yml
notebooks/.keep
quickfire/__init__.py
quickfire/clean_text.py
quickfire.egg-info/PKG-INFO
quickfire.egg-info/SOURCES.txt
quickfire.egg-info/dependency_links.txt
quickfire.egg-info/not-zip-safe
quickfire.egg-info/requires.txt
quickfire.egg-info/top_level.txt
quickfire/data/.keep
scripts/quickfire-run
tests/__init__.py
tests/test_clean_text.py