Metadata-Version: 1.0
Name: quickfire
Version: 1.0
Summary: Project Description
Home-page: UNKNOWN
Author: UNKNOWN
Author-email: UNKNOWN
License: UNKNOWN
Platform: UNKNOWN
